wait_for/__init__.py
wait_for-1.2.0.dist-info/AUTHORS
wait_for-1.2.0.dist-info/LICENSE
wait_for-1.2.0.dist-info/METADATA
wait_for-1.2.0.dist-info/WHEEL
wait_for-1.2.0.dist-info/pbr.json
wait_for-1.2.0.dist-info/top_level.txt
wait_for-1.2.0.dist-info/RECORD
