Metadata-Version: 2.1
Name: wait-for
Version: 1.2.0
Summary: A waiting based utility with decorator and logger support
Home-page: https://github.com/RedHatQE/wait_for
Author: Peter Savage
Author-email: psavage@redhat.com
License: Apache
Keywords: setup,distutils
Platform: UNKNOWN
Classifier: Development Status :: 4 - Beta
Classifier: Environment :: Console
Classifier: Intended Audience :: Developers
Classifier: Operating System :: OS Independent
Classifier: Programming Language :: Python :: 3
Classifier: Programming Language :: Python :: 3.6
Classifier: Programming Language :: Python :: 3.7
Classifier: Programming Language :: Python :: 3.8
Classifier: Programming Language :: Python :: 3.9
Classifier: Topic :: Utilities
Requires-Python: >=3.6
License-File: LICENSE
